ou_docs_server/__about__.py
ou_docs_server/__init__.py
ou_docs_server-0.0.1.dist-info/METADATA
ou_docs_server-0.0.1.dist-info/WHEEL
ou_docs_server-0.0.1.dist-info/licenses/LICENSE.txt
ou_docs_server-0.0.1.dist-info/RECORD
