Metadata-Version: 2.1
Name: ou-docs-server
Version: 0.0.1
Project-URL: Documentation, https://github.com/unknown/ou-docs-server#readme
Project-URL: Issues, https://github.com/unknown/ou-docs-server/issues
Project-URL: Source, https://github.com/unknown/ou-docs-server
Author-email: Mark Hall <mark.hall@work.room3b.eu>
License-Expression: MIT
License-File: LICENSE.txt
Classifier: Development Status :: 4 - Beta
Classifier: Programming Language :: Python
Classifier: Programming Language :: Python :: 3.7
Classifier: Programming Language :: Python :: 3.8
Classifier: Programming Language :: Python :: 3.9
Classifier: Programming Language :: Python :: 3.10
Classifier: Programming Language :: Python :: 3.11
Classifier: Programming Language :: Python :: Implementation :: CPython
Classifier: Programming Language :: Python :: Implementation :: PyPy
Requires-Python: >=3.7
Requires-Dist: aiofiles<24,>=23
Requires-Dist: fastapi[all]
Requires-Dist: pydantic-settings<3,>=2
Requires-Dist: pydantic<3,>=2
Requires-Dist: python-multipart
Requires-Dist: uvicorn[standard]
